{
  "TilePassDatas": [
    {
      "ActivityID": 100001,
      "Index": 0,
      "TargetNum": 0,
      "FreeRewards": 6,
      "FreeRewardsNum": 1,
      "VipRewards": 1,
      "VipRewardsNum": 3000,
      "CardFreeRewards": 6,
      "CardFreeRewardsNum": 1,
      "CardVipRewards": 1,
      "CardVipRewardsNum": 3000
    },
    {
      "ActivityID": 100001,
      "Index": 1,
      "TargetNum": 1,
      "FreeRewards": 4,
      "FreeRewardsNum": 1,
      "VipRewards": 2,
      "VipRewardsNum": 1,
      "CardFreeRewards": 4,
      "CardFreeRewardsNum": 1,
      "CardVipRewards": 2,
      "CardVipRewardsNum": 1
    },
    {
      "ActivityID": 100001,
      "Index": 2,
      "TargetNum": 2,
      "FreeRewards": 2,
      "FreeRewardsNum": 1,
      "VipRewards": 3,
      "VipRewardsNum": 1,
      "CardFreeRewards": 51,
      "CardFreeRewardsNum": 1,
      "CardVipRewards": 55,
      "CardVipRewardsNum": 1
    },
    {
      "ActivityID": 100001,
      "Index": 3,
      "TargetNum": 3,
      "FreeRewards": 5,
      "FreeRewardsNum": 1,
      "VipRewards": 6,
      "VipRewardsNum": 1,
      "CardFreeRewards": 5,
      "CardFreeRewardsNum": 1,
      "CardVipRewards": 6,
      "CardVipRewardsNum": 1
    },
    {
      "ActivityID": 100001,
      "Index": 4,
      "TargetNum": 5,
      "FreeRewards": 1,
      "FreeRewardsNum": 100,
      "VipRewards": 4,
      "VipRewardsNum": 1,
      "CardFreeRewards": 1,
      "CardFreeRewardsNum": 100,
      "CardVipRewards": 4,
      "CardVipRewardsNum": 1
    },
    {
      "ActivityID": 100001,
      "Index": 5,
      "TargetNum": 6,
      "FreeRewards": "18,2",
      "FreeRewardsNum": "30,1",
      "VipRewards": "18,21,1",
      "VipRewardsNum": "60,2,400",
      "CardFreeRewards": "52,18",
      "CardFreeRewardsNum": "1,30",
      "CardVipRewards": "53,18,21",
      "CardVipRewardsNum": "1,60,2"
    },
    {
      "ActivityID": 100001,
      "Index": 6,
      "TargetNum": 7,
      "FreeRewards": 21,
      "FreeRewardsNum": 1,
      "VipRewards": 5,
      "VipRewardsNum": 1,
      "CardFreeRewards": 21,
      "CardFreeRewardsNum": 1,
      "CardVipRewards": 5,
      "CardVipRewardsNum": 1
    },
    {
      "ActivityID": 100001,
      "Index": 7,
      "TargetNum": 8,
      "FreeRewards": 4,
      "FreeRewardsNum": 1,
      "VipRewards": 2,
      "VipRewardsNum": 2,
      "CardFreeRewards": 4,
      "CardFreeRewardsNum": 1,
      "CardVipRewards": 2,
      "CardVipRewardsNum": 2
    },
    {
      "ActivityID": 100001,
      "Index": 8,
      "TargetNum": 9,
      "FreeRewards": 23,
      "FreeRewardsNum": 30,
      "VipRewards": 3,
      "VipRewardsNum": 2,
      "CardFreeRewards": 52,
      "CardFreeRewardsNum": 1,
      "CardVipRewards": 53,
      "CardVipRewardsNum": 1
    },
    {
      "ActivityID": 100001,
      "Index": 9,
      "TargetNum": 10,
      "FreeRewards": 3,
      "FreeRewardsNum": 1,
      "VipRewards": 5,
      "VipRewardsNum": 2,
      "CardFreeRewards": 3,
      "CardFreeRewardsNum": 1,
      "CardVipRewards": 5,
      "CardVipRewardsNum": 2
    },
    {
      "ActivityID": 100001,
      "Index": 10,
      "TargetNum": 11,
      "FreeRewards": "5,6",
      "FreeRewardsNum": "1,1",
      "VipRewards": "23,4,6,2,1",
      "VipRewardsNum": "60,2,2,2,400",
      "CardFreeRewards": "5,6",
      "CardFreeRewardsNum": "1,1",
      "CardVipRewards": "23,4,6,2,53",
      "CardVipRewardsNum": "60,2,2,2,1"
    },
    {
      "ActivityID": 100001,
      "Index": 11,
      "TargetNum": 12,
      "FreeRewards": 4,
      "FreeRewardsNum": 1,
      "VipRewards": 21,
      "VipRewardsNum": 2,
      "CardFreeRewards": 4,
      "CardFreeRewardsNum": 1,
      "CardVipRewards": 21,
      "CardVipRewardsNum": 2
    },
    {
      "ActivityID": 100001,
      "Index": 12,
      "TargetNum": 13,
      "FreeRewards": 1,
      "FreeRewardsNum": 100,
      "VipRewards": 2,
      "VipRewardsNum": 2,
      "CardFreeRewards": 18,
      "CardFreeRewardsNum": 30,
      "CardVipRewards": 2,
      "CardVipRewardsNum": 2
    },
    {
      "ActivityID": 100001,
      "Index": 13,
      "TargetNum": 14,
      "FreeRewards": 18,
      "FreeRewardsNum": 30,
      "VipRewards": 6,
      "VipRewardsNum": 2,
      "CardFreeRewards": 52,
      "CardFreeRewardsNum": 1,
      "CardVipRewards": 54,
      "CardVipRewardsNum": 1
    },
    {
      "ActivityID": 100001,
      "Index": 14,
      "TargetNum": 15,
      "FreeRewards": 2,
      "FreeRewardsNum": 1,
      "VipRewards": 24,
      "VipRewardsNum": 60,
      "CardFreeRewards": 2,
      "CardFreeRewardsNum": 1,
      "CardVipRewards": 24,
      "CardVipRewardsNum": 60
    },
    {
      "ActivityID": 100001,
      "Index": 15,
      "TargetNum": 20,
      "FreeRewards": "4,6",
      "FreeRewardsNum": "1,1",
      "VipRewards": "5,4,2,1",
      "VipRewardsNum": "2,2,2,600",
      "CardFreeRewards": "4,6",
      "CardFreeRewardsNum": "1,1",
      "CardVipRewards": "5,4,2,1",
      "CardVipRewardsNum": "2,2,2,600"
    },
    {
      "ActivityID": 100001,
      "Index": 16,
      "TargetNum": 20,
      "FreeRewards": 3,
      "FreeRewardsNum": 1,
      "VipRewards": 3,
      "VipRewardsNum": 2,
      "CardFreeRewards": 53,
      "CardFreeRewardsNum": 1,
      "CardVipRewards": 54,
      "CardVipRewardsNum": 1
    },
    {
      "ActivityID": 100001,
      "Index": 17,
      "TargetNum": 20,
      "FreeRewards": 24,
      "FreeRewardsNum": 30,
      "VipRewards": 2,
      "VipRewardsNum": 2,
      "CardFreeRewards": 24,
      "CardFreeRewardsNum": 30,
      "CardVipRewards": 2,
      "CardVipRewardsNum": 2
    },
    {
      "ActivityID": 100001,
      "Index": 18,
      "TargetNum": 20,
      "FreeRewards": 6,
      "FreeRewardsNum": 1,
      "VipRewards": 5,
      "VipRewardsNum": 2,
      "CardFreeRewards": 6,
      "CardFreeRewardsNum": 1,
      "CardVipRewards": 5,
      "CardVipRewardsNum": 2
    },
    {
      "ActivityID": 100001,
      "Index": 19,
      "TargetNum": 20,
      "FreeRewards": 2,
      "FreeRewardsNum": 1,
      "VipRewards": 18,
      "VipRewardsNum": 60,
      "CardFreeRewards": 2,
      "CardFreeRewardsNum": 1,
      "CardVipRewards": 18,
      "CardVipRewardsNum": 60
    },
    {
      "ActivityID": 100001,
      "Index": 20,
      "TargetNum": 25,
      "FreeRewards": "1,4,5",
      "FreeRewardsNum": "100,1,1",
      "VipRewards": "1,2,4,5,6",
      "VipRewardsNum": "600,2,2,2,2",
      "CardFreeRewards": "1,4,53",
      "CardFreeRewardsNum": "100,1,1",
      "CardVipRewards": "1,2,4,5,54",
      "CardVipRewardsNum": "600,2,2,2,1"
    },
    {
      "ActivityID": 100001,
      "Index": 21,
      "TargetNum": 25,
      "FreeRewards": 18,
      "FreeRewardsNum": 30,
      "VipRewards": 3,
      "VipRewardsNum": 2,
      "CardFreeRewards": 18,
      "CardFreeRewardsNum": 30,
      "CardVipRewards": 3,
      "CardVipRewardsNum": 2
    },
    {
      "ActivityID": 100001,
      "Index": 22,
      "TargetNum": 25,
      "FreeRewards": 21,
      "FreeRewardsNum": 1,
      "VipRewards": 6,
      "VipRewardsNum": 2,
      "CardFreeRewards": 21,
      "CardFreeRewardsNum": 1,
      "CardVipRewards": 6,
      "CardVipRewardsNum": 2
    },
    {
      "ActivityID": 100001,
      "Index": 23,
      "TargetNum": 25,
      "FreeRewards": 23,
      "FreeRewardsNum": 30,
      "VipRewards": 2,
      "VipRewardsNum": 2,
      "CardFreeRewards": 23,
      "CardFreeRewardsNum": 30,
      "CardVipRewards": 2,
      "CardVipRewardsNum": 2
    },
    {
      "ActivityID": 100001,
      "Index": 24,
      "TargetNum": 25,
      "FreeRewards": 6,
      "FreeRewardsNum": 1,
      "VipRewards": 18,
      "VipRewardsNum": 60,
      "CardFreeRewards": 6,
      "CardFreeRewardsNum": 1,
      "CardVipRewards": 18,
      "CardVipRewardsNum": 60
    },
    {
      "ActivityID": 100001,
      "Index": 25,
      "TargetNum": 30,
      "FreeRewards": "18,5,2",
      "FreeRewardsNum": "30,1,1",
      "VipRewards": "24,4,6,2,1",
      "VipRewardsNum": "60,3,3,3,600",
      "CardFreeRewards": "18,5,53",
      "CardFreeRewardsNum": "30,1,1",
      "CardVipRewards": "24,4,6,1,55",
      "CardVipRewardsNum": "60,3,3,600,1"
    },
    {
      "ActivityID": 100001,
      "Index": 26,
      "TargetNum": 30,
      "FreeRewards": 1,
      "FreeRewardsNum": 200,
      "VipRewards": 2,
      "VipRewardsNum": 3,
      "CardFreeRewards": 1,
      "CardFreeRewardsNum": 200,
      "CardVipRewards": 2,
      "CardVipRewardsNum": 3
    },
    {
      "ActivityID": 100001,
      "Index": 27,
      "TargetNum": 30,
      "FreeRewards": 3,
      "FreeRewardsNum": 1,
      "VipRewards": 5,
      "VipRewardsNum": 3,
      "CardFreeRewards": 3,
      "CardFreeRewardsNum": 1,
      "CardVipRewards": 5,
      "CardVipRewardsNum": 3
    },
    {
      "ActivityID": 100001,
      "Index": 28,
      "TargetNum": 30,
      "FreeRewards": 2,
      "FreeRewardsNum": 2,
      "VipRewards": 6,
      "VipRewardsNum": 3,
      "CardFreeRewards": 54,
      "CardFreeRewardsNum": 1,
      "CardVipRewards": 55,
      "CardVipRewardsNum": 1
    },
    {
      "ActivityID": 100001,
      "Index": 29,
      "TargetNum": 30,
      "FreeRewards": 6,
      "FreeRewardsNum": 2,
      "VipRewards": 4,
      "VipRewardsNum": 3,
      "CardFreeRewards": 6,
      "CardFreeRewardsNum": 2,
      "CardVipRewards": 4,
      "CardVipRewardsNum": 3
    },
    {
      "ActivityID": 100001,
      "Index": 30,
      "TargetNum": 50,
      "FreeRewards": "5,4,6,2",
      "FreeRewardsNum": "3,3,3,3",
      "VipRewards": "1,18,23,4,6,2",
      "VipRewardsNum": "2000,60,60,3,3,3",
      "CardFreeRewards": "55,4,6,2",
      "CardFreeRewardsNum": "1,3,3,3",
      "CardVipRewards": "1,55,54,4,6,2",
      "CardVipRewardsNum": "2000,1,1,3,3,3"
    }
  ]
}