{
  "AllLayerTileDict": {
    "1": {
      "113": "1",
      "125": "1",
      "23": "1",
      "215": "1",
      "102": "-2",
      "104": "-2"
    },
    "2": {
      "22": "1",
      "214": "1",
      "24": "1",
      "216": "1",
      "97": "1",
      "109": "1",
      "129": "1",
      "141": "1",
      "102": "-2",
      "104": "-2"
    },
    "3": {
      "81": "1",
      "93": "1",
      "113": "1",
      "125": "1",
      "145": "1",
      "157": "1",
      "21": "1",
      "213": "1",
      "23": "1",
      "215": "1",
      "25": "1",
      "217": "1",
      "102": "-2",
      "104": "-2"
    },
    "4": {
      "161": "1",
      "173": "1",
      "129": "1",
      "141": "1",
      "97": "1",
      "109": "1",
      "65": "1",
      "77": "1",
      "20": "1",
      "212": "1",
      "22": "1",
      "214": "1",
      "24": "1",
      "216": "1",
      "26": "1",
      "218": "1",
      "102": "-2",
      "104": "-2"
    },
    "5": {
      "177": "1",
      "189": "1",
      "145": "1",
      "157": "1",
      "113": "1",
      "125": "1",
      "81": "1",
      "93": "1",
      "49": "1",
      "61": "1",
      "19": "1",
      "211": "1",
      "21": "1",
      "213": "1",
      "23": "1",
      "215": "1",
      "25": "1",
      "217": "1",
      "27": "1",
      "219": "1",
      "102": "-2",
      "104": "-2"
    },
    "6": {
      "193": "1",
      "205": "1",
      "161": "1",
      "173": "1",
      "129": "1",
      "141": "1",
      "97": "1",
      "109": "1",
      "65": "1",
      "77": "1",
      "33": "1",
      "45": "1",
      "20": "1",
      "212": "1",
      "22": "1",
      "214": "1",
      "24": "1",
      "216": "1",
      "26": "1",
      "218": "1",
      "102": "-2",
      "104": "-2"
    },
    "7": {
      "209": "1",
      "177": "1",
      "189": "1",
      "145": "1",
      "157": "1",
      "113": "1",
      "125": "1",
      "81": "1",
      "93": "1",
      "49": "1",
      "61": "1",
      "17": "1",
      "19": "1",
      "211": "1",
      "21": "1",
      "213": "1",
      "23": "1",
      "215": "1",
      "25": "1",
      "217": "1",
      "27": "1",
      "219": "1",
      "29": "1",
      "221": "1",
      "102": "-2",
      "104": "-2"
    },
    "8": {
      "194": "1",
      "204": "1",
      "162": "1",
      "172": "1",
      "130": "1",
      "140": "1",
      "98": "1",
      "108": "1",
      "66": "1",
      "76": "1",
      "34": "1",
      "36": "1",
      "196": "1",
      "38": "1",
      "198": "1",
      "40": "1",
      "200": "1",
      "42": "1",
      "202": "1",
      "44": "1",
      "102": "-2",
      "104": "-2"
    },
    "9": {
      "179": "1",
      "147": "1",
      "155": "1",
      "115": "1",
      "123": "1",
      "83": "1",
      "91": "1",
      "51": "1",
      "53": "1",
      "181": "1",
      "55": "1",
      "183": "1",
      "57": "1",
      "185": "1",
      "59": "1",
      "187": "1",
      "102": "-2",
      "104": "-2"
    },
    "10": {
      "102": "-2",
      "104": "-2"
    },
    "11": {
      "102": "-2",
      "104": "-2"
    },
    "12": {
      "102": "-2",
      "104": "-2"
    },
    "13": {
      "102": "-2",
      "104": "-2"
    },
    "14": {
      "102": "-2",
      "104": "-2"
    }
  },
  "GoldTileCount": 0,
  "TileItemArray": [],
  "TotalItemNum": 14,
  "MoveVect": [
    0.0,
    0.0
  ],
  "TileTotalNum": 0,
  "TileLevelHardType": "Normal",
  "TotalCount": 168
}