{
  "AllLayerTileDict": {
    "1": {
      "129": 1,
      "141": 1,
      "97": 1,
      "109": 1,
      "119": 1,
      "117": 1,
      "121": 1,
      "115": 1,
      "123": 1,
      "163": -2,
      "167": -2,
      "171": -2,
      "197": -3,
      "201": -3
    },
    "2": {
      "114": 1,
      "124": 1,
      "83": 1,
      "91": 1,
      "101": 1,
      "103": 1,
      "105": 1,
      "163": -2,
      "167": -2,
      "171": -2,
      "197": -3,
      "201": -3
    },
    "3": {
      "99": 1,
      "107": 1,
      "68": 1,
      "74": 1,
      "86": 1,
      "88": 1,
      "163": -2,
      "167": -2,
      "171": -2,
      "197": -3,
      "201": -3
    },
    "4": {
      "82": 1,
      "92": 1,
      "201": -3,
      "49": 1,
      "51": 1,
      "59": 1,
      "197": -3,
      "61": 1,
      "53": 1,
      "57": 1,
      "171": -2,
      "163": -2,
      "71": 1,
      "167": -2,
      "100": 1,
      "103": 1,
      "106": 1
    },
    "5": {
      "34": 1,
      "44": 1,
      "167": -2,
      "56": 1,
      "36": 1,
      "42": 1,
      "197": -3,
      "163": -2,
      "67": 1,
      "75": 1,
      "171": -2,
      "54": 1,
      "201": -3,
      "100": 1,
      "103": 1,
      "106": 1
    },
    "6": {
      "19": 1,
      "27": 1,
      "51": 1,
      "59": 1,
      "37": 1,
      "41": 1,
      "55": 1,
      "163": -2,
      "167": -2,
      "171": -2,
      "197": -3,
      "201": -3,
      "100": 1,
      "103": 1,
      "106": 1
    },
    "7": {
      "50": 1,
      "60": 1,
      "100": 1,
      "163": -2,
      "36": 1,
      "42": 1,
      "201": -3,
      "167": -2,
      "54": 1,
      "56": 1,
      "197": -3,
      "171": -2,
      "103": 1,
      "106": 1
    }
  },
  "TileItemArray": [],
  "TotalItemNum": 11,
  "MoveVect": [
    0.0,
    0.5
  ],
  "TileTotalNum": 0,
  "TileLevelHardType": "Normal",
  "TotalCount": 99
}