{
  "AllLayerTileDict": {
    "1": {
      "115": "-2",
      "117": "-2",
      "119": "-2",
      "121": "-2",
      "123": "-2",
      "19": "-2",
      "27": "-2",
      "220": "-1",
      "210": "0",
      "188": "-1",
      "178": "0",
      "21": "-2",
      "25": "-2",
      "55": "-2",
      "183": "-2"
    },
    "2": {
      "115": "-2",
      "117": "-2",
      "119": "-2",
      "121": "-2",
      "123": "-2",
      "19": "-2",
      "27": "-2",
      "220": "-1",
      "210": "0",
      "188": "-1",
      "178": "0",
      "21": "-2",
      "25": "-2",
      "55": "-2",
      "183": "-2"
    },
    "3": {
      "115": "-2",
      "117": "-2",
      "119": "-2",
      "121": "-2",
      "123": "-2",
      "19": "-2",
      "27": "-2",
      "220": "-1",
      "210": "0",
      "188": "-1",
      "178": "0",
      "21": "-2",
      "25": "-2",
      "55": "-2",
      "183": "-2"
    },
    "4": {
      "115": "-2",
      "117": "-2",
      "119": "-2",
      "121": "-2",
      "123": "-2",
      "19": "-2",
      "27": "-2",
      "220": "-1",
      "210": "0",
      "188": "-1",
      "178": "0",
      "21": "-2",
      "25": "-2",
      "55": "-2",
      "183": "-2"
    },
    "5": {
      "115": "-2",
      "117": "-2",
      "119": "-2",
      "121": "-2",
      "123": "-2",
      "19": "-2",
      "27": "-2",
      "220": "-1",
      "210": "0",
      "188": "-1",
      "178": "0",
      "21": "-2",
      "25": "-2",
      "55": "-2",
      "183": "-2"
    },
    "6": {
      "19": "-2",
      "220": "-1",
      "27": "-2",
      "210": "0",
      "115": "-2",
      "117": "-2",
      "119": "-2",
      "121": "-2",
      "123": "-2",
      "188": "-1",
      "178": "0",
      "21": "-2",
      "25": "-2",
      "55": "-2",
      "183": "-2"
    },
    "7": {
      "19": "-2",
      "21": "-2",
      "25": "-2",
      "27": "-2",
      "115": "-2",
      "117": "-2",
      "119": "-2",
      "121": "-2",
      "123": "-2",
      "220": "-1",
      "188": "-1",
      "178": "0",
      "210": "0",
      "55": "-2",
      "183": "-2"
    }
  },
  "TileItemArray": [],
  "TotalItemNum": 12,
  "MoveVect": [
    0.0,
    0.0
  ],
  "TileTotalNum": 0,
  "TileLevelHardType": "Normal",
  "TotalCount": 105
}